LICENSE
MANIFEST.in
README.rst
setup.cfg
setup.py
tox.ini
docs/Makefile
docs/authors.rst
docs/conf.py
docs/contributing.rst
docs/history.rst
docs/index.rst
docs/installation.rst
docs/make.bat
docs/modules.rst
docs/pyislands.rst
docs/readme.rst
docs/usage.rst
pyislands/__init__.py
pyislands/creation.py
pyislands/evolution.py
pyislands/selection.py
pyislands/types.py
pyislands.egg-info/PKG-INFO
pyislands.egg-info/SOURCES.txt
pyislands.egg-info/dependency_links.txt
pyislands.egg-info/not-zip-safe
pyislands.egg-info/top_level.txt
pyislands/archipelago/__init__.py
pyislands/archipelago/assimilation.py
pyislands/archipelago/migration.py
pyislands/archipelago/multiprocess.py
pyislands/archipelago/nonparallel.py
pyislands/archipelago/topology.py
pyislands/example/__init__.py
pyislands/example/evolvetsp.py
pyislands/example/maintsp.py
pyislands/ga/__init__.py
pyislands/ga/generational.py
pyislands/ga/steady.py
pyislands/permutation/__init__.py
pyislands/permutation/generate.py
pyislands/permutation/inversions.py
pyislands/permutation/crossover/__init__.py
pyislands/permutation/crossover/cx.py
pyislands/permutation/crossover/ox1.py
pyislands/permutation/crossover/pmx.py
pyislands/permutation/mutation/__init__.py
pyislands/permutation/mutation/ecm.py
pyislands/permutation/mutation/rsm.py
pyislands/permutation/tsp/__init__.py
pyislands/permutation/tsp/graph.py
pyislands/permutation/tsp/mutation.py
tests/__init__.py
tests/testexample.py
tests/testimport.py
tests/permutation/__init__.py
tests/permutation/testgenerate.py
tests/permutation/crossover/__init__.py
tests/permutation/crossover/testcx.py
tests/permutation/crossover/testox1.py
tests/permutation/crossover/testpmx.py
tests/permutation/mutation/__init__.py
tests/permutation/mutation/testecm.py
tests/permutation/mutation/testrsm.py
tests/permutation/tsp/__init__.py
tests/permutation/tsp/testgraph.py
tests/permutation/tsp/testmutation.py