Metadata-Version: 1.1
Name: pyislands
Version: 0.1.3
Summary: PyIslands contains an implementation of islands genetic algorithms.
Home-page: https://github.com/sglumac/pyislands
Author: Slaven Glumac
Author-email: slaven.glumac@gmail.com
License: MIT
Keywords: pyislands
Platform: UNKNOWN
Classifier: Development Status :: 2 - Pre-Alpha
Classifier: Intended Audience :: Developers
Classifier: License :: OSI Approved :: MIT License
Classifier: Natural Language :: English
Classifier: Programming Language :: Python :: 2.7
Classifier: Programming Language :: Python :: 3.4
Classifier: Programming Language :: Python :: Implementation :: PyPy
